ansys/edb/core/__init__.py
ansys/edb/core/database.py
ansys/edb/core/edb_defs.py
ansys/edb/core/session.py
ansys/edb/core/definition/__init__.py
ansys/edb/core/definition/bondwire_def.py
ansys/edb/core/definition/component_def.py
ansys/edb/core/definition/component_model.py
ansys/edb/core/definition/component_pin.py
ansys/edb/core/definition/component_property.py
ansys/edb/core/definition/dataset_def.py
ansys/edb/core/definition/debye_model.py
ansys/edb/core/definition/die_property.py
ansys/edb/core/definition/dielectric_material_model.py
ansys/edb/core/definition/djordjecvic_sarkar_model.py
ansys/edb/core/definition/ic_component_property.py
ansys/edb/core/definition/io_component_property.py
ansys/edb/core/definition/material_def.py
ansys/edb/core/definition/material_property_thermal_modifier.py
ansys/edb/core/definition/multipole_debye_model.py
ansys/edb/core/definition/package_def.py
ansys/edb/core/definition/padstack_def.py
ansys/edb/core/definition/padstack_def_data.py
ansys/edb/core/definition/port_property.py
ansys/edb/core/definition/rlc_component_property.py
ansys/edb/core/definition/solder_ball_property.py
ansys/edb/core/geometry/__init__.py
ansys/edb/core/geometry/arc_data.py
ansys/edb/core/geometry/point3d_data.py
ansys/edb/core/geometry/point_data.py
ansys/edb/core/geometry/polygon_data.py
ansys/edb/core/geometry/r_tree.py
ansys/edb/core/geometry/triangle3d_data.py
ansys/edb/core/hierarchy/__init__.py
ansys/edb/core/hierarchy/cell_instance.py
ansys/edb/core/hierarchy/component_group.py
ansys/edb/core/hierarchy/group.py
ansys/edb/core/hierarchy/hierarchy_obj.py
ansys/edb/core/hierarchy/inst_array.py
ansys/edb/core/hierarchy/layout_component.py
ansys/edb/core/hierarchy/model.py
ansys/edb/core/hierarchy/netlist_model.py
ansys/edb/core/hierarchy/pin_group.py
ansys/edb/core/hierarchy/pin_pair_model.py
ansys/edb/core/hierarchy/sparameter_model.py
ansys/edb/core/hierarchy/spice_model.py
ansys/edb/core/hierarchy/structure3d.py
ansys_edb_core-0.2.5.dist-info/licenses/LICENSE
ansys_edb_core-0.2.5.dist-info/WHEEL
ansys_edb_core-0.2.5.dist-info/METADATA
ansys_edb_core-0.2.5.dist-info/RECORD
